svgutils/__init__.py
svgutils/compose.py
svgutils/templates.py
svgutils/transform.py
svgutils-0.3.3.dist-info/LICENSE
svgutils-0.3.3.dist-info/METADATA
svgutils-0.3.3.dist-info/WHEEL
svgutils-0.3.3.dist-info/top_level.txt
svgutils-0.3.3.dist-info/RECORD
