Metadata-Version: 2.1
Name: svgutils
Version: 0.3.3
Summary: Python SVG editor
Home-page: https://svgutils.readthedocs.io
Author: Bartosz Telenczuk
Author-email: bartosz.telenczuk@gmail.com
License: UNKNOWN
Download-URL: https://github.com/btel/svg_utils/archive/v0.3.3.tar.gz
Platform: UNKNOWN
Classifier: Development Status :: 4 - Beta
Classifier: Environment :: Console
Classifier: Intended Audience :: Science/Research
Classifier: License :: OSI Approved :: MIT License
Classifier: Operating System :: OS Independent
Classifier: Programming Language :: Python :: 3.5
Classifier: Programming Language :: Python :: 2.7
Classifier: Topic :: Multimedia :: Graphics :: Editors :: Vector-Based
Classifier: Topic :: Scientific/Engineering :: Visualization
Classifier: Topic :: Text Processing :: Markup
Requires-Dist: lxml
